wildboar/version.py
wildboar/__init__.py
wildboar/base.py
wildboar/tree/_cptree.c
wildboar/tree/_base.py
wildboar/tree/_ctree.cpython-311-darwin.so
wildboar/tree/_ptree.py
wildboar/tree/__init__.py
wildboar/tree/_cptree.cpython-311-darwin.so
wildboar/tree/_cptree.pyx
wildboar/tree/_ctree.c
wildboar/tree/_ctree.pyx
wildboar/tree/_tree.py
wildboar/metrics/_counterfactual.py
wildboar/metrics/__init__.py
wildboar/metrics/_cluster.py
wildboar/ensemble/__init__.py
wildboar/ensemble/_ensemble.py
wildboar/ensemble/_elastic.py
wildboar/explain/_importance.py
wildboar/explain/__init__.py
wildboar/explain/counterfactual/_nn.py
wildboar/explain/counterfactual/_helper.py
wildboar/explain/counterfactual/_sf.py
wildboar/explain/counterfactual/__init__.py
wildboar/explain/counterfactual/_proto.py
wildboar/datasets/outlier.py
wildboar/datasets/preprocess.py
wildboar/datasets/_filter.py
wildboar/datasets/__init__.py
wildboar/datasets/_repository.py
wildboar/distance/_neighbors.py
wildboar/distance/_manifold.py
wildboar/distance/_cdistance.cpython-311-darwin.so
wildboar/distance/_cneighbors.cpython-311-darwin.so
wildboar/distance/_elastic.cpython-311-darwin.so
wildboar/distance/_elastic.pyx
wildboar/distance/_distance.py
wildboar/distance/_cdistance.pxd
wildboar/distance/__init__.pxd
wildboar/distance/_mass.cpython-311-darwin.so
wildboar/distance/_mass.pyx
wildboar/distance/_metric.pyx
wildboar/distance/__init__.py
wildboar/distance/_cmatrix_profile.pyx
wildboar/distance/_mass.c
wildboar/distance/_metric.cpython-311-darwin.so
wildboar/distance/_cmatrix_profile.pxd
wildboar/distance/_matrix_profile.py
wildboar/distance/_metric.pxd
wildboar/distance/_elastic.c
wildboar/distance/_mass.pxd
wildboar/distance/_cdistance.pyx
wildboar/distance/_cneighbors.c
wildboar/distance/_cneighbors.pyx
wildboar/distance/_cmatrix_profile.cpython-311-darwin.so
wildboar/distance/_elastic.pxd
wildboar/distance/_multi_metric.py
wildboar-1.2.1.dist-info/RECORD
wildboar-1.2.1.dist-info/LICENSE
wildboar-1.2.1.dist-info/WHEEL
wildboar-1.2.1.dist-info/top_level.txt
wildboar-1.2.1.dist-info/METADATA
