Metadata-Version: 2.2
Name: wildboar
Version: 1.2.1
Summary: Time series learning with Python.
Author-email: Isak Samsten <isak@samsten.se>
License: BSD 3-Clause License
Project-URL: Homepage, https://wildboar.dev
Project-URL: Documentation, https://wildboar.dev
Project-URL: Repository, https://github.com/wildboar-foundation/wildboar
Project-URL: Bug Tracker, https://github.com/wildboar-foundation/wildboar/issues
Keywords: machine learning,time series,counterfactual explanation
Classifier: Programming Language :: Python :: 3
Classifier: Topic :: Scientific/Engineering :: Artificial Intelligence
Classifier: Intended Audience :: Science/Research
Classifier: License :: OSI Approved :: BSD License
Classifier: Operating System :: Microsoft :: Windows
Classifier: Operating System :: POSIX
Classifier: Operating System :: Unix
Classifier: Operating System :: MacOS
Requires-Python: >=3.9
License-File: LICENSE
Requires-Dist: numpy>=1.19.5
Requires-Dist: scipy>=1.6.0
Requires-Dist: scikit-learn<1.6a,>=1.3
Provides-Extra: outliers
Requires-Dist: networkx; extra == "outliers"
